exb_sdk-0.2.1.dist-info/METADATA
exb_sdk-0.2.1.dist-info/WHEEL
exb_sdk-0.2.1.dist-info/licenses/LICENSE
exb_sdk/__init__.py
exb_sdk/__version__.py
exb_sdk/py.typed
exb_sdk/workflow_client/__init__.py
exb_sdk/workflow_client/_api_constants.py
exb_sdk/workflow_client/client.py
exb_sdk/workflow_client/exceptions.py
exb_sdk/workflow_client/test_client.py
exb_sdk-0.2.1.dist-info/RECORD
