Metadata-Version: 2.1
Name: exb-sdk
Version: 0.2.1
Summary: SDK for working with ExB (app.exb.de)
Author-Email: Riccardo Padoan <riccardo.padoan@exb.de>, Lukas Jesche <lukas.jesche@exb.de>, Andreas Kohl <andreas.kohl@exb.de>
Maintainer-Email: Riccardo Padoan <riccardo.padoan@exb.de>, Lukas Jesche <lukas.jesche@exb.de>, Andreas Kohl <andreas.kohl@exb.de>
License: MIT
Classifier: Development Status :: 2 - Pre-Alpha
Classifier: Intended Audience :: Developers
Classifier: License :: OSI Approved :: MIT License
Classifier: Natural Language :: English
Classifier: Operating System :: OS Independent
Classifier: Programming Language :: Python
Classifier: Programming Language :: Python :: 3
Classifier: Programming Language :: Python :: 3 :: Only
Classifier: Programming Language :: Python :: 3.11
Classifier: Programming Language :: Python :: 3.12
Classifier: Typing :: Typed
Project-URL: Homepage, https://github.com/ExB-Group/exb-sdk
Project-URL: Documentation, https://ExB-Group.github.io/exb-sdk
Project-URL: Changelog, https://github.com/ExB-Group/exb-sdk/releases
Project-URL: Repository, https://github.com/ExB-Group/exb-sdk
Project-URL: Issue tracker, https://github.com/ExB-Group/exb-sdk/issues
Requires-Python: <3.13,>=3.11
Requires-Dist: httpx>=0.27.0
Requires-Dist: loguru>=0.7.2
Requires-Dist: tenacity>=8.5.0
